falkordb/__init__.py
falkordb/asyncio/__init__.py
falkordb/asyncio/cluster.py
falkordb/asyncio/falkordb.py
falkordb/asyncio/graph.py
falkordb/asyncio/graph_schema.py
falkordb/asyncio/query_result.py
falkordb/cluster.py
falkordb/edge.py
falkordb/exceptions.py
falkordb/execution_plan.py
falkordb/falkordb.py
falkordb/graph.py
falkordb/graph_schema.py
falkordb/helpers.py
falkordb/node.py
falkordb/path.py
falkordb/query_result.py
falkordb/sentinel.py
kiarina_falkordb-1.3.0.dist-info/LICENSE
kiarina_falkordb-1.3.0.dist-info/METADATA
kiarina_falkordb-1.3.0.dist-info/WHEEL
kiarina_falkordb-1.3.0.dist-info/RECORD
