Metadata-Version: 2.3
Name: kiarina-falkordb
Version: 1.3.0
Summary: FalkorDB Python client (fork with additional fixes)
Keywords: FalkorDB,GraphDB,Cypher
Author: FalkorDB inc
Author-email: info@falkordb.com
Requires-Python: >=3.9,<4.0
Classifier: Programming Language :: Python :: 3
Classifier: Programming Language :: Python :: 3.9
Classifier: Programming Language :: Python :: 3.10
Classifier: Programming Language :: Python :: 3.11
Classifier: Programming Language :: Python :: 3.12
Classifier: Programming Language :: Python :: 3.13
Classifier: Programming Language :: Python :: 3.14
Requires-Dist: python-dateutil (>=2.9.0,<3.0.0)
Requires-Dist: redis (>=7.0.0,<8.0.0)
Project-URL: Homepage, https://github.com/kiarina/falkordb-py
Project-URL: Repository, https://github.com/kiarina/falkordb-py
